aragora_client/__init__.py
aragora_client/client.py
aragora_client/exceptions.py
aragora_client/py.typed
aragora_client/types.py
aragora_client/websocket.py
aragora_client-2.1.10.dist-info/METADATA
aragora_client-2.1.10.dist-info/WHEEL
aragora_client-2.1.10.dist-info/RECORD
