Metadata-Version: 2.4
Name: aragora-client
Version: 2.1.10
Summary: Python SDK for Aragora multi-agent debate framework
Project-URL: Homepage, https://aragora.ai
Project-URL: Documentation, https://docs.aragora.ai/sdk/python
Project-URL: Repository, https://github.com/an0mium/aragora
Project-URL: Issues, https://github.com/an0mium/aragora/issues
Author-email: Aragora Team <team@aragora.ai>
License-Expression: MIT
Keywords: ai,anthropic,aragora,debate,llm,multi-agent,openai,sdk
Classifier: Development Status :: 4 - Beta
Classifier: Intended Audience :: Developers
Classifier: License :: OSI Approved :: MIT License
Classifier: Programming Language :: Python :: 3
Classifier: Programming Language :: Python :: 3.10
Classifier: Programming Language :: Python :: 3.11
Classifier: Programming Language :: Python :: 3.12
Classifier: Topic :: Scientific/Engineering :: Artificial Intelligence
Classifier: Typing :: Typed
Requires-Python: >=3.10
Requires-Dist: httpx>=0.25.0
Requires-Dist: pydantic>=2.0.0
Requires-Dist: websockets>=12.0
Provides-Extra: dev
Requires-Dist: mypy>=1.0; extra == 'dev'
Requires-Dist: pytest-asyncio>=0.21; extra == 'dev'
Requires-Dist: pytest-httpx>=0.30; extra == 'dev'
Requires-Dist: pytest>=7.0; extra == 'dev'
Requires-Dist: ruff>=0.1; extra == 'dev'
